Metadata-Version: 2.1
Name: active-learning
Version: 0.3.0
Summary: Active Learning With Rich feedabck
Home-page: https://github.com/tonywang124/TREWS-AL
Author: Lucas Rosen, Hossein Soleimani, Tony Wang
Author-email: lrosen27@jhu.edu
License: UNKNOWN
Platform: UNKNOWN
Classifier: Programming Language :: Python :: 3
Classifier: License :: OSI Approved :: MIT License
Classifier: Operating System :: OS Independent
